tihclient/__about__.py
tihclient/__init__.py
tihclient/base.py
tihclient/tih_api.py
tihclient-0.0.3.dist-info/METADATA
tihclient-0.0.3.dist-info/WHEEL
tihclient-0.0.3.dist-info/licenses/LICENSE.txt
tihclient-0.0.3.dist-info/RECORD
