Metadata-Version: 2.1
Name: tihclient
Version: 0.0.3
Summary: TIH api client
Project-URL: Documentation, https://github.com/furyhawk/tihclient#readme
Project-URL: Issues, https://github.com/furyhawk/tihclient/issues
Project-URL: Source, https://github.com/furyhawk/tihclient
Author-email: Teck Meng <furyx@hotmail.com>
License-Expression: MIT
License-File: LICENSE.txt
Keywords: api,client,data,dataframe,pandas,python,tih
Classifier: Development Status :: 4 - Beta
Classifier: Programming Language :: Python
Classifier: Programming Language :: Python :: 3.11
Classifier: Programming Language :: Python :: Implementation :: CPython
Classifier: Programming Language :: Python :: Implementation :: PyPy
Requires-Python: >=3.11
